rpmol/__init__.py
rpmol/rpmol.py
rpmol-0.2.1.dist-info/LICENSE
rpmol-0.2.1.dist-info/METADATA
rpmol-0.2.1.dist-info/WHEEL
rpmol-0.2.1.dist-info/entry_points.txt
rpmol-0.2.1.dist-info/top_level.txt
rpmol-0.2.1.dist-info/RECORD
