Metadata-Version: 2.1
Name: rpmol
Version: 0.2.1
Summary: Paquete para la conversión y manipulación de datos estructurales.
Home-page: https://github.com/usuario/rpmol
Author: Rubén Prieto-Díaz
Author-email: ruben.prietodiaz@icm.uu.se
License: MIT
Platform: UNKNOWN
Classifier: Programming Language :: Python :: 3
Classifier: License :: OSI Approved :: MIT License
Classifier: Operating System :: MacOS
License-File: LICENSE
Requires-Dist: pandas
Requires-Dist: rdkit
Requires-Dist: openpyxl
Requires-Dist: reportlab
